algepy/DiscreteFunctions.py
algepy/QuadraticStructures.py
algepy/SingletonStructures.py
algepy/__init__.py
algepy_tools-0.1.2.dist-info/LICENSE.txt
algepy_tools-0.1.2.dist-info/METADATA
algepy_tools-0.1.2.dist-info/WHEEL
algepy_tools-0.1.2.dist-info/top_level.txt
algepy_tools-0.1.2.dist-info/RECORD
