Metadata-Version: 2.2
Name: algepy-tools
Version: 0.1.2
Summary: A Python library for efficient number theory and abstract algebra, featuring tools for primality testing, factorization, and advanced modular arithmetic.
Home-page: https://github.com/sumaddury/algepy
Author: Sucheer Maddury
Author-email: Sucheer Maddury <sm2939@cornell.edu>
Project-URL: Homepage, https://github.com/sumaddury/algepy
Project-URL: Documentation, https://sumaddury.github.io/AlgePy/
Project-URL: Repository, https://github.com/sumaddury/algepy
Keywords: number theory,algebra,abstract algebra,primality,factorization,modular arithmetic
Classifier: Development Status :: 3 - Alpha
Classifier: Intended Audience :: Science/Research
Classifier: License :: OSI Approved :: Apache Software License
Classifier: Programming Language :: Python :: 3
Classifier: Topic :: Scientific/Engineering :: Mathematics
Classifier: Topic :: Software Development :: Libraries
Requires-Python: >=3.7
License-File: LICENSE.txt
Dynamic: author
Dynamic: home-page
Dynamic: requires-python
